{
    "$schema": "https://schema.management.azure.com/schemas/2019-04-01/deploymentTemplate.json#",
    "contentVersion": "1.0.0.0",
    "parameters": {},
    "variables": {},
    "resources": [
        {
            "type": "Microsoft.VirtualMachineImages/imageTemplates",
            "apiVersion": "2022-07-01",
            "dependsOn": [],
            "name": "<imageName>",
            "location": "<location>",
            "identity": {
                "type": "UserAssigned",
                "userAssignedIdentities": {
                    "/subscriptions/<subscriptionID>/resourceGroups/<rgName>/providers/Microsoft.ManagedIdentity/userAssignedIdentities/<identityName>": {}
                }
            },
            "properties": {
                "source": {
                    "offer": "visualstudioplustools",
                    "publisher": "microsoftvisualstudio",
                    "sku": "vs-2022-ent-general-win11-m365-gen2",
                    "type": "PlatformImage",
                    "version": "latest"
                },
                "buildTimeoutInMinutes": 0,
                "vmProfile": {
                    "vmSize": "Standard_DS2_v2",
                    "osDiskSizeGB": 64,
                    "userAssignedIdentities": [
                        "/subscriptions/<subscriptionID>/resourceGroups/<rgName>/providers/Microsoft.ManagedIdentity/userAssignedIdentities/<identityName>"
                    ]
                },
                "distribute": [
                    {
                        "type": "ManagedImage",
                        "galleryImageId": "/subscriptions/<subscriptionID>/resourceGroups/<rgName>/providers/Microsoft.Compute/galleries/<sharedImageGalName>/images/<imageDefName>",
                        "imageId": "/subscriptions/<subscriptionID>/resourceGroups/<rgName>/providers/Microsoft.Compute/images/<imageName>",
                        "runOutputName": "runOutputManagedImage",
                        "location": "<location>",
                        "replicationlocations": [],
                         "targetRegions": [
                            {
                                "name": "<location>"
                            }
                        ]   
                    }
                ]
            },
            "tags": {
                "division": "IT",
                "Environment": "Dev-Workstation",
                "Role": "Back-End-Engineer"
            }
        }
    ]
}
